<?xml version="1.0" encoding="utf-8"?>
<root ArabicWord="منزل بالواعر" EnglishWord="MNRL BALWA3R">
   <WordPart>
      <Letter letter="M">521 51,523 45,524 45,527 45,531 45,536 48,537 49,538 50,538 51,539 52,539 53,539 54,538 55,538 56,537 56,536 57,535 57,534 58,532 58,531 58,530 58,529 57,527 57,526 56,525 55,524 54,524 53,523 52,522 51,522 50,522 49,522 48,522 47,523 47,523 48,523 49,524 50,524 52,524 53,524 54,523 55,523 56,523 57,522 58,521 59,520 60,519 60</Letter>
      <Letter letter="N">519 60,517 60,516 60,515 60,514 59,513 59,512 58,511 58,511 57,510 56,510 55,510 54,510 53,509 53,509 52,510 52,510 53,510 54,510 55,510 57,509 58,509 59,508 60,507 60,506 61,505 62</Letter>
      <Letter letter="R">505 62,504 62,503 62,502 62,501 62,500 62,499 61,498 61,497 60,496 59,495 58,495 57,494 56,493 55,493 54,492 54,492 53,492 54,493 55,493 56,493 57,493 58,494 59,494 61,494 62,494 64,494 65,493 67,492 69,492 70,491 72,489 73,487 75,485 76,483 78,481 79,478 80,475 81,472 81,469 81,467 81,464 81,461 81,459 80,457 80,455 79,454 78</Letter>
   </WordPart>
   <WordPart>
      <Letter letter="L">449 45,448 40,447 36,447 35,448 37,448 38,451 45,452 48,452 51,453 53,454 56,455 59,456 62,456 66,456 68,456 71,456 74,455 76,454 78,453 80,452 81,450 82,447 83,445 83,443 83,440 83,438 82,435 81,433 79,432 78,430 76,429 74,428 72,428 70,428 69,429 67,429 66,430 66</Letter>
   </WordPart>
   <WordPart>
      <Letter letter="B">393 59,393 58,396 59,397 59,398 61,399 62,395 66,393 66,392 67,390 67,388 68,386 68,385 69,383 69,381 69,379 70,378 70</Letter>
      <Letter letter="A">378 70,376 70,375 70,374 70,373 70,372 70,371 70,371 69,371 68,371 67,371 66,371 65,371 63,371 62,371 60,370 59,370 57,369 55,369 53,369 51,369 49,369 47,369 46,369 45,369 44,370 45,370 46,371 47,371 48,372 50,373 52,374 55</Letter>
   </WordPart>
   <WordPart>
      <Letter letter="L">355 52,354 47,353 48,354 54,354 55,354 57,355 58,355 60,355 61,355 63,355 64,354 66,354 67,353 69,352 70</Letter>
      <Letter letter="W">352 70,351 71,349 72,348 73,346 73,344 73,342 73,341 73,339 72,337 71,336 70,335 68,334 67,334 66,334 64,334 63,335 62,335 61,336 61,337 60,338 60,339 60,339 61,340 62,341 62,342 63,343 64,344 66,344 67,345 69,345 71,346 73,346 75,345 77,345 79,344 81,343 82,342 84,340 85,339 87,337 88,335 88,333 89,331 89,328 90,326 90,324 89,321 89,319 89,317 88,315 88,313 87</Letter>
   </WordPart>
   <WordPart>
      <Letter letter="A">309 47,309 45,311 49,312 53,313 55,313 57,314 59,314 61,318 69,318 70,318 71</Letter>
   </WordPart>
   <WordPart>
      <Letter letter="3">289 63,288 60,287 61,284 61,283 62,282 62,281 63,280 64,279 65,281 69,282 70,283 70,284 71,286 72,287 72,288 72,289 73,290 73,291 73,291 74,290 74,289 75,287 75,286 76,284 76,282 77,280 77,278 77,276 77,275 77</Letter>
      <Letter letter="R">275 77,273 76,272 76,271 75,271 74,270 73,270 72,269 70,269 69,269 68,268 67,268 66,268 65,268 64,268 63,268 64,268 65,268 66,268 67,269 68,269 70,269 72,270 74,270 76,270 78,270 80,269 82,269 84,268 86,266 88,265 90,263 91,260 93,258 94,255 95,253 96,250 97,247 97,245 97,243 97,241 97,240 96,238 96,238 95</Letter>
   </WordPart>
</root>