<?xml version="1.0" encoding="utf-8"?>
<root ArabicWord="شويقي" EnglishWord="SWYFY">
   <WordPart>
      <Letter letter="S">757 62,757 57,757 55,758 56,758 57,760 61,760 62,761 63,761 65,761 66,761 67,761 68,761 69,761 70,760 70,759 71,758 71,757 70,756 70,755 69,754 68,753 67,753 66,752 65,751 64,751 63,750 62,750 63,750 64,751 65,751 66,751 67,751 68,751 69,751 70,750 70,750 71,749 71,748 71,747 70,746 70,746 69,745 68,745 67,744 66,744 65,744 64,743 64,742 68,741 68,740 69,739 70,738 70,737 71,735 72,733 73,731 74,729 74,726 75</Letter>
      <Letter letter="W">726 75,724 76,721 76,718 77,715 77,712 77,709 77,707 77,704 77,702 77,700 76,699 75,698 74,697 72,697 71,697 70,697 69,698 68,699 67,700 67,701 67,703 67,704 68,706 69,708 70,710 72,711 73,713 75,714 77,715 79,715 81,715 83,715 85,713 87,711 88,707 90,703 91,697 92,692 93,686 94,680 94,674 94,669 95,665 94,662 93,660 92</Letter>
   </WordPart>
   <WordPart>
      <Letter letter="Y">666 65,666 62,665 60,666 61,666 62,667 62,669 67,669 68,669 69,669 70,669 71,669 72,668 73,667 74,666 74,665 75,664 75,663 75,662 76,661 76,660 77</Letter>
      <Letter letter="F">660 77,659 77,658 77,657 78,656 78,655 78,654 78,653 78,652 78,651 78,650 78,649 78,648 77,647 77,646 77,645 77,644 76,643 76,642 75,641 75,640 75,640 74,639 74,638 74,637 73,636 72,635 71,635 70,634 70,634 69,633 68,632 68,631 68,630 68,629 67,628 66,628 65,629 64,630 64,631 63,632 63,633 63,634 63,635 63,636 63,637 64,638 64,638 65,639 65,640 66,641 67,642 68,642 69,642 70,642 71,641 72,641 73,641 74,640 74,639 75,639 76,638 76,637 77,636 77,635 78,634 78,633 79,632 79</Letter>
      <Letter letter="Y">632 79,630 80,629 80,628 80,627 80,626 80,625 80,624 79,623 79,622 78,621 77,620 76,619 75,618 74,616 72,615 71,614 70,612 70,610 69,609 69,607 69,605 69,603 70,602 70,601 71,600 72,599 73,599 74,599 75,600 76,601 77,602 78,602 79,603 80,604 81,605 83,605 84,605 85,605 86,604 87,603 88,601 89,598 90,594 90,589 90,584 90,579 90,574 90,570 89,566 88,563 87,561 85,560 82,560 80,562 78,565 75,569 73,575 71</Letter>
   </WordPart>
</root>