<?xml version="1.0" encoding="utf-8"?>
<root ArabicWord="منزل خير" EnglishWord="MNRL 7YR">
   <WordPart>
      <Letter letter="M">553 123,552 119,551 117,551 108,552 103,554 99,559 93,560 92,562 92,565 92,567 93,570 94,573 95,576 96,579 97,581 99,583 101,585 103,586 105,586 107,586 109,585 111,584 113,582 115,581 117,578 118,576 120,573 121,570 121,567 121,564 121,560 120,557 118,554 116,551 114,548 111,546 109,545 106,544 104,544 102,544 101,544 100,545 99,545 100,546 101,547 102,547 103,548 105,548 107,548 109,548 111,548 113,547 115,546 116,545 118,542 119</Letter>
      <Letter letter="N">542 119,522 120,516 116,512 112,509 109,508 107,507 105,506 104,506 103,505 102,505 101,505 100,505 101,505 102,505 103,506 104,506 105,506 107,506 108,506 109,506 111,505 113,504 114,503 115,501 116</Letter>
      <Letter letter="R">501 116,496 119,494 119,492 119,490 118,488 117,486 116,485 114,484 113,482 111,481 109,481 108,479 106,480 107,480 108,483 119,484 121,484 124,484 127,484 130,483 135,481 138,480 140,477 142,474 144,471 146,467 147,463 148,459 149,455 149,451 148,447 146,443 144,440 141,438 137</Letter>
   </WordPart>
   <WordPart>
      <Letter letter="L">443 55,441 69,442 85,443 110,443 117,444 124,444 130,444 137,444 143,444 148,443 153,442 157,440 161,437 164,434 166,430 168,426 169,421 169,416 168,410 167,405 165,401 162,396 158,392 154,389 149</Letter>
   </WordPart>
   <WordPart>
      <Letter letter="7">336 111,333 97,359 92,363 91,366 90,369 89,372 88,374 87,376 85,376 84,377 83,377 82,376 82,375 82,374 83,372 85,370 87,368 90,366 93,363 96,360 100,358 103,355 107,352 109,350 111,347 113,345 114,342 115,339 115,336 114,333 113,330 112,327 111,324 110</Letter>
      <Letter letter="Y">324 110,322 108,319 107,318 106,316 105,315 105,315 104,314 105,314 106,314 107,314 108,314 110,314 112,314 113,314 115,314 116,314 117,313 118,312 118,310 118</Letter>
      <Letter letter="R">310 118,309 118,307 117,306 117,304 116,302 114,301 113,299 112,298 111,297 110,296 109,295 108,295 109,295 110,296 111,296 113,297 115,297 118,298 120,299 123</Letter>
   </WordPart>
</root>