<?xml version="1.0" encoding="utf-8"?>
<root ArabicWord="بئرالحفي" EnglishWord="BYRAL7FY">
   <WordPart>
      <Letter letter="B">741 36,741 37,741 38,741 41,742 43,742 45,743 47,744 49,745 50,745 51,746 52,747 53,747 54,747 55,748 55,748 56,748 57,748 58,748 59,748 60,747 60,747 61,746 61,745 61</Letter>
      <Letter letter="Y">745 61,745 62,744 62,743 62,742 62,741 62,740 62,739 62,738 62,737 62,736 61,735 61,734 60,733 60,732 59,731 59,730 58,727 54,727 53,726 52,726 51,726 50,725 49,725 48,725 47,725 46,724 46,724 45,724 46,724 47,724 48,724 49,724 50,724 51,725 52,725 53,725 54,726 55,726 56,726 57,727 58,727 59,726 59,726 60,725 61,724 61,723 62,722 62,721 63,720 63</Letter>
      <Letter letter="R">720 63,719 63,718 63,717 63,716 63,715 63,714 63,713 63,712 63,711 62,710 62,709 62,708 61,707 60,706 60,705 59,704 58,703 58,703 57,702 57,702 56,701 55,701 54,700 54,700 53,699 52,698 51,698 50,697 50,696 49,695 48,694 48,693 48,693 49,694 50,695 51,696 52,696 53,697 53,697 54,698 54,698 55,699 55,699 56,700 56,700 57,701 58,701 59,702 59,702 60,703 61,703 62,703 63,703 64,703 65,703 66,703 67,703 68,703 69,703 70,702 71,702 72,701 72,701 73,700 74,699 75,698 75,697 76,696 77,695 77,693 78,691 79,689 79,687 79,685 80,683 80,681 80,679 80,678 80,676 79,674 79,673 78,671 77,669 76,668 74,667 72,666 70</Letter>
   </WordPart>
   <WordPart>
      <Letter letter="A">645 13,645 14,645 17,646 20,646 23,647 28,649 33,649 35,650 36,650 38,651 40,651 41,652 43,652 44,652 46,653 47,653 49,654 50,654 51,654 52,655 54,655 55,655 56,655 57,655 58</Letter>
   </WordPart>
   <WordPart>
      <Letter letter="L">624 22,626 19,627 22,628 25,628 28,629 30,630 31,631 35,631 36,632 37,632 38,632 39,632 40,632 41,632 42,632 43,632 44,632 45,632 46,632 47,632 48,631 49,631 50,630 51,629 52,628 53,627 53,626 53,625 54,624 54</Letter>
      <Letter letter="7">624 54,623 54,622 54,621 54,620 53,619 53,618 53,617 53,616 53,615 53,614 53,613 53,612 53,611 53,610 53,609 53,608 53, Inf Inf,  585 52,587 49,587 48,591 45,592 45,596 44,598 43,599 43,600 43,601 44,602 44,603 44,603 45,604 45,605 46,606 46,607 46,608 47,609 47,610 47,611 47,612 47,613 47,614 47,614 46,615 46,616 46,617 45,616 45,615 45,615 46,614 46,613 47,612 47,612 48,611 49,610 50,609 51,608 52,608 53,607 53,607 54,606 54,606 55,605 55,604 56,603 56,602 56,601 57,600 57,599 57,598 58,597 58,595 58,594 58,592 58,591 58,589 58,587 59,586 59,584 59,582 59</Letter>
      <Letter letter="F">582 59,580 59,578 58,577 58,575 58,573 58,572 57,571 57,569 57,568 56,567 55,566 55,566 54,565 53,564 52,564 51,564 50,563 49,563 47,563 46,563 45,563 44,563 43,564 42,564 41,564 40,565 40,565 39,566 39,566 38,567 38,568 39,568 40,569 41,569 42,570 43,570 44,571 45,571 46,571 47,572 48,572 49,572 50,572 51,572 52,572 53,572 54,572 55,571 56,571 57,570 58,570 59,569 59,569 60,568 60,567 60,567 61,566 61,565 61,564 61,563 61,562 61</Letter>
      <Letter letter="Y">562 61,561 61,560 61,559 60,558 60,558 59,557 58,556 57,555 56,554 55,553 54,553 52,552 51,551 50,550 50,550 49,549 48,548 47,547 46,546 46,545 46,544 46,543 46,542 47,541 48,540 48,540 49,539 50,539 51,538 51,538 52,538 53,538 54,538 55,539 55,539 56,540 56,541 57,542 58,543 58,544 58,544 59,545 59,546 59,546 60,547 60,548 60,548 61,549 61,550 62,551 63,552 63,552 64,553 64,553 65,553 66,554 66,554 67,554 68,554 69,554 70,553 70,553 71,552 72,552 73,551 73,550 74,549 75,547 75,546 76,544 76,543 76,541 77,539 77,538 77,536 76,534 76,532 75,531 75,529 74,527 72,526 71,524 70,522 68,521 66,520 63,519 61,518 58,518 55,518 52,518 49</Letter>
   </WordPart>
</root>