<?xml version="1.0" encoding="utf-8"?>
<root ArabicWord="السمران " EnglishWord="ALSMRAN ">
   <WordPart>
      <Letter letter="A">699 102,699 97,699 94,699 91,698 88,698 85,695 72,695 70,694 70,694 71,694 73,694 75,694 78,694 82,695 86,696 90,697 94,699 99,700 103,702 107,703 111,703 115,704 118,704 120</Letter>
   </WordPart>
   <WordPart>
      <Letter letter="L">658 82,657 79,657 78,657 77,657 76,658 79,659 83,659 88,660 94,660 97,661 100,661 102,661 105,661 108,661 110,660 113,660 115,659 117,658 118,657 119</Letter>
      <Letter letter="S">657 119,656 120,655 121,653 121,652 121,650 121,648 120,646 119,644 118,641 116,639 114,637 112,635 110,633 108,631 105,630 103,628 100,627 98,626 97,626 95,625 94,626 95,626 96,627 98,627 99,628 101,629 103,629 105,630 107,630 109,630 111,630 113,630 114,630 116,630 117,629 118,628 118,627 119,626 119,624 119,623 119,621 118,619 117,617 116,615 115,614 113,613 111,611 109,610 107,609 105,609 103,608 102,607 101,607 100,607 99,607 100,607 101,607 102,607 104,608 106,608 107,608 109,608 111,608 113,608 114,607 115,607 116,606 117,605 117,604 117,602 116,601 116,599 115,597 113,596 112,594 111,593 110,592 109,592 108,591 108,591 109,591 110,591 111,591 113,591 114,591 116,591 117,590 118,589 119,588 120,586 120,583 121,581 121,577 120</Letter>
      <Letter letter="M">577 120,574 120,571 119, Inf Inf,  551 112,554 109,557 108,558 109,561 110,563 113,564 114,565 116,564 120,563 121,562 122,560 122,557 122,555 122,553 121,550 121,548 119,546 118,545 116,543 115,542 113,542 112,542 111,541 110,541 112,541 113,540 114,540 116,539 118,538 119,537 121,535 122,534 123,532 124,530 125,528 125,525 125,523 126,521 126,519 126,517 126,515 126</Letter>
      <Letter letter="R">515 126,513 127,511 128,510 129,508 131,505 133,503 135,501 138,498 141,495 144,492 147,489 150,486 152,483 154,480 156,477 157,475 157,473 157,471 157,469 156,468 154,467 152,467 149,467 147,468 144,469 141,470 139,472 137</Letter>
   </WordPart>
   <WordPart>
      <Letter letter="A">473 98,470 94,469 92,468 90,468 87,467 85,467 83,466 81,466 80,465 78,465 79,466 82,471 96,472 100,474 103,476 107,477 110,479 113,480 115</Letter>
   </WordPart>
   <WordPart>
      <Letter letter="N">436 108,436 114,438 118,443 127,442 136,440 137,437 139,433 140,429 141,424 142,418 143,411 143,405 142,399 142,393 140,388 138,383 136,380 133,378 130,377 127,376 124,376 121,377 119,378 117,379 115</Letter>
   </WordPart>
</root>