<?xml version="1.0" encoding="utf-8"?>
<root ArabicWord="شيبة" EnglishWord="SYBH">
   <WordPart>
      <Letter letter="S">460 63,460 66,460 71,459 73,459 74,459 75,458 76,457 77,456 76,456 75,455 74,455 73,454 71,454 70,453 68,453 67,453 65,452 64,452 63,451 63,451 64,451 65,451 66,451 67,450 68,450 70,450 72,449 73,449 74,449 76,449 77,448 78,447 78,447 77,446 76,446 75,445 74,444 73,444 72,443 71,443 70,443 69,442 69,442 70,441 71,441 73,440 74,440 75,439 77,438 78,437 79,435 80,434 81</Letter>
      <Letter letter="Y">434 81,433 82,432 82,431 82,429 82,428 82,427 81,427 80,426 79,426 77,426 76,426 75,426 74,427 73,427 72,427 71,426 72,425 72,424 73,423 74,421 75,418 76,416 77,413 79</Letter>
      <Letter letter="B">413 79,410 80,407 81,403 81,400 82,397 83,393 83,390 84,387 84,384 84,382 83,380 83,378 82,377 82,376 81,375 80,375 79, Inf Inf,  378 74,377 73,378 74,378 75,378 78,377 79,377 80,376 82,375 83,374 84,373 84</Letter>
      <Letter letter="H">373 84,367 87,366 87,365 86,364 85,364 84,364 83,364 82,363 80,363 79,363 78,363 77,363 76,362 75,361 75,360 75,359 76,357 77,355 77,352 78,350 79,348 80,347 81,345 82,344 83,343 84,342 85,344 86,345 86,346 86,348 86,350 85,353 85,355 85,358 84,360 84</Letter>
   </WordPart>
</root>