<?xml version="1.0" encoding="utf-8"?>
<root ArabicWord="سوسة" EnglishWord="SWSH">
   <WordPart>
      <Letter letter="S">507 61,506 61,506 60,507 60,508 62,510 64,513 69,513 70,513 71,514 72,514 73,514 74,513 74,513 75,512 75,511 75,510 75,509 75,508 75,507 74,506 74,505 73,504 73,504 72,503 72,502 71,502 70,501 70,501 69,500 68,499 67,498 66,497 65,497 66,498 66,498 67,498 68,499 69,499 70,500 71,500 72,500 73,500 74,500 75,500 76,500 77,499 78,498 78,497 78,496 78,495 78,494 78,493 77,492 77,491 76,490 76,490 75,489 75,488 74,487 73,486 72,485 71,484 70,484 69,483 68,483 67,482 66,482 67,482 68,483 69,483 70,483 71,483 72,483 73,484 74,484 75,484 76,484 77,483 78,483 79,482 80,481 80,481 81,480 81,479 82,477 82</Letter>
      <Letter letter="W">477 82,476 82,475 83,474 83,472 83,471 83,469 83,468 83,467 83,465 84,464 84,462 84,461 84,460 84,459 84,458 84,457 83,456 83,455 83,454 82,453 81,453 80,453 79,454 78,455 78,455 77,456 77,457 77,458 77,459 77,460 77,461 77,462 78,463 78,464 79,465 80,466 81,466 82,466 83,466 84,466 86,466 87,465 88,464 89,463 90,462 92,461 93,459 94,457 94,455 95,452 95,450 96,448 95,446 95</Letter>
   </WordPart>
   <WordPart>
      <Letter letter="S">434 62,434 61,433 60,434 61,434 62,435 63,435 65,436 67,436 70,436 72,433 75,432 75,431 74,430 73,429 72,428 71,428 70,428 69,427 68,427 67,427 66,426 66,426 65,426 66,426 67,426 68,426 69,426 70,426 71,426 72,426 73,426 74,425 75,425 76,424 76,423 77,422 77,421 77,420 76,419 75,419 74,418 73,418 72,417 71,417 70,417 69,416 68,416 67,416 68,416 69,415 70,415 71,415 72,415 74,414 75,414 76,413 77,413 78,412 79,411 79,410 80</Letter>
      <Letter letter="H">410 80,409 80,408 79,407 79,407 78,406 77,405 76,404 74,403 73,402 71,401 70,401 68,400 67,398 66,397 65,396 64,394 64,393 63,391 63,390 63,388 63,386 63,384 64,382 64,380 65,378 66,377 68,375 69,374 70,373 71,372 72,371 73,371 74,371 75,372 76,374 76,376 76,378 76,381 75,383 74,386 73,389 73,391 71,393 71,395 70,396 69</Letter>
   </WordPart>
</root>