<?xml version="1.0" encoding="utf-8"?>
<root ArabicWord="بو عطّوش" EnglishWord="BW 36WS">
   <WordPart>
      <Letter letter="B">645 46,641 39,643 41,645 44,650 50,652 55,650 63,648 64,646 66,643 67,641 67,638 68</Letter>
      <Letter letter="W">638 68,635 68,632 68,629 67,626 66,624 65,622 64,621 63,620 62,619 61,619 60,619 59,620 58,621 58,622 58,624 59,625 60,626 62,627 63,628 66,629 68,629 70,629 73,629 75,627 77,625 79,623 81,620 83,617 84,613 85,609 86,606 87,602 86,599 86,597 85</Letter>
   </WordPart>
   <WordPart>
      <Letter letter="3">584 47,585 53,588 53,590 53,592 53,594 53,595 53,597 52,598 52,598 53,597 54,596 55,594 56,592 57,589 59,587 61,583 62,580 64,576 65,573 67,569 68,565 68,562 69,558 69</Letter>
      <Letter letter="6">558 69,555 69,552 69,550 69,548 68,546 67,544 65,542 64,542 62,541 60,540 58,540 55,540 53,541 51,541 49,542 47,543 45,544 44,545 43,546 42,547 41,548 41,549 42,550 42,551 43,551 44,552 46,552 47,552 49,551 51,550 53,548 56,547 58,544 59,542 61,539 63,536 64,532 66,529 67</Letter>
      <Letter letter="W">529 67,526 68,523 68,520 69,518 69,516 68,514 68,513 67,512 66,512 65,512 64,511 63,511 62,512 61,512 60,513 59,514 59,515 60,517 61,518 62,519 64,520 66,521 68,522 70,522 72,522 74,521 76,520 78,518 80,515 81,512 83,509 83,506 84,503 84,500 83,497 82</Letter>
   </WordPart>
   <WordPart>
      <Letter letter="S">487 58,486 59,487 61,488 63,489 64,489 66,490 67,491 69,491 70,490 72,489 72,488 72,487 72,486 71,485 70,483 70,482 69,481 68,480 67,479 67,480 67,480 68,480 69,481 70,481 71,481 72,481 73,480 74,479 74,478 74,477 73,476 72,475 72,474 71,473 70,473 69,472 69,472 68,471 68,471 69,472 70,472 71,472 72,473 73,473 75,473 76,473 78,472 79,471 81,470 82,468 84,465 85,463 86,460 87,457 87,453 87,450 86,447 86,444 85,442 84,440 82,438 81,437 79,436 76,436 74,437 72,438 69,440 66,441 63,444 61,446 58</Letter>
   </WordPart>
</root>