<?xml version="1.0" encoding="utf-8"?>
<root ArabicWord="القصر " EnglishWord="ALF8R ">
   <WordPart>
      <Letter letter="A">739 77,740 75,740 74,740 73,741 72,741 71,742 71,742 72,742 74,742 78,742 80,741 83,741 87,741 90,740 94,740 98,740 102,740 106,740 109,740 112,740 115,741 117,741 119,741 121,742 122,742 123,742 122,742 121</Letter>
   </WordPart>
   <WordPart>
      <Letter letter="L">715 82,715 81,714 95,714 97,714 99,714 101,714 103,715 105,715 107,715 108,715 110,715 111,715 112,714 114,714 115,713 116,713 117,712 118,711 118,710 119,709 120,707 120,706 121,704 121,703 122,701 122,700 122</Letter>
      <Letter letter="F">700 122,698 123,697 123,696 123,695 122,694 122,693 121,692 121,692 120,691 119,691 117,690 116,690 115,690 113,690 112,690 111,690 110,690 109,691 109,692 110,693 111,694 112,694 113,695 113,695 114,695 115,695 116,695 117,694 118,693 118,692 118,691 119,689 119,687 119,685 119,683 119,680 119,676 119,673 119</Letter>
      <Letter letter="8">673 119,669 118,665 118,661 118,658 117,655 117,653 117,651 117,650 116,649 116,648 116,649 115,650 115, Inf Inf,  632 125,634 102,635 101,635 100,636 100,637 100,638 100,638 101,639 101,640 102,641 102,642 103,643 104,645 105,646 105,647 106,649 107,650 108,651 108,652 109,652 110,653 110,653 111,654 111,654 112,654 113,654 114,654 115,653 116,652 117,651 117,649 118,647 119,644 119,642 120,638 120,634 121,629 121,624 121,619 121,614 121,609 121</Letter>
      <Letter letter="R">609 121,604 121,601 121,598 120,596 119,594 119,594 118,593 117,594 116,594 115,595 114,596 113,596 112,595 112,595 113,594 114,594 115,594 116,595 117,595 119,595 120,596 122,596 125,597 127,597 129,597 132,597 134,596 136,594 138,592 140,589 141,585 142,581 143,576 144,569 144,562 145,554 145,545 144</Letter>
   </WordPart>
</root>