<?xml version="1.0" encoding="utf-8"?>
<root ArabicWord="نبّر" EnglishWord="NBR">
   <WordPart>
      <Letter letter="N">736 106,735 104,735 103,735 101,735 102,735 103,735 104,735 105,735 108,735 109,735 110,734 111,734 112,733 113,732 114,731 115,730 115,729 116,728 116,727 116,725 117,724 117,719 117,718 118,716 118,715 118,713 118,712 118</Letter>
      <Letter letter="B">712 118,711 117,710 117,709 117,708 117,708 116,707 116,706 115,705 115,705 114,704 114,704 113,703 113,703 112,703 111,702 111,702 110,702 109,702 108,701 108,701 107,701 106,701 107,701 108,700 109,700 110,699 111,699 112,698 113,697 113,696 114,695 115,693 115,692 116,690 117,688 117,686 118,684 118,681 118,679 118,677 118</Letter>
      <Letter letter="R">677 118,675 118,674 118,672 118,670 118,669 118,668 117,667 117,666 117,665 117,664 116,663 116,663 115,662 115,662 114,662 113,661 112,661 111,661 110,661 111,661 112,661 113,661 114,661 115,661 116,661 117,660 119,660 120,660 122,659 123,659 125,658 127,657 129,656 131,655 133,653 135,652 137,649 139,647 141,644 142,641 144,638 145,635 146,632 146,629 147,626 147,623 147,621 147,619 147,619 146</Letter>
   </WordPart>
</root>