<?xml version="1.0" encoding="utf-8"?>
<root ArabicWord="اللوزة " EnglishWord="ALLWRH ">
   <WordPart>
      <Letter letter="A">593 20,592 17,592 16,591 15,591 14,590 13,590 14,590 15,591 16,591 18,594 26,596 29,597 32,599 36,601 40,604 44,606 49,608 53,610 58,613 62,615 66,616 70,618 74,620 77,621 80,622 83,623 84,623 86,623 87,623 88</Letter>
   </WordPart>
   <WordPart>
      <Letter letter="L">564 25,563 24,563 23,563 25,564 26,565 29,579 53,580 56,582 59,584 62,585 65,586 68,588 70,589 73,590 75,591 77,591 79,592 81,592 82,593 84,593 85,593 86,593 87,592 87,592 88,591 88,590 88,589 88,588 88,586 88,585 87</Letter>
      <Letter letter="L">585 87,583 86,581 85,579 84,577 83,575 81,573 79,571 77,569 75,567 73,565 70,563 67,561 65,560 62,558 59,556 56,554 54,553 51,551 49,550 46,549 44,547 42,546 40,545 38,544 36,543 35,542 34,541 33,541 32,540 31,540 30,540 31,540 32,541 33,541 35,542 36,542 38,543 40,544 42,545 44,546 46,548 49,549 51,550 53,552 56,553 58,555 60,556 63,557 65,558 67,559 69,560 71,561 72,561 74,562 75,562 77,562 78,562 79,562 80,561 81,561 82,560 83,559 84,558 85,556 85,554 86,552 86,550 87,547 87,545 88,542 88,539 88,535 89,532 89,529 90,525 90</Letter>
      <Letter letter="W">525 90,521 91,518 91,514 91,510 91,507 92,503 92,500 92,497 92,494 91,492 91,489 90,487 90,485 89,483 88,481 87,480 86,478 86,477 84,477 83,476 82,475 81,475 79,474 78,474 77,474 76,474 75,474 74,474 73,474 72,475 72,475 73,476 73,477 73,478 74,480 75,482 76,484 76,486 77,489 79,491 80,493 81,496 82,498 83,500 84,502 86,503 87,505 88,509 92,509 93,510 94,510 95,511 96,511 97,511 98,510 99,509 100,509 101,508 102,507 102,506 103,504 104,503 105,501 105,499 106,497 106,495 107,492 108,489 108,486 109,482 109,478 110,474 111,469 111,464 112,459 113,453 113,447 114,441 114,435 115,429 115,423 116,417 116,412 116,406 116,401 116,397 116,392 116,389 115,386 115</Letter>
   </WordPart>
   <WordPart>
      <Letter letter="R">394 71,393 70,393 71,394 72,395 73,397 74,399 76,405 79,408 82,413 87,413 88,413 89,413 90,413 92,412 93,411 94,410 95,409 96,408 97,406 98,403 99,401 100,398 101,395 103,391 104,388 105,384 106,379 107,375 108,371 108,367 109,364 109,360 110,357 110,354 110,352 109,350 109,348 108,347 107,346 106,345 105</Letter>
   </WordPart>
   <WordPart>
      <Letter letter="H">319 72,317 71,319 71,320 70,322 70,326 70,335 71,350 77,351 78,352 79,352 80,352 81,351 82,350 83,349 84,347 85,344 86,342 87,339 88,335 88,332 88,329 88,327 88,324 88,322 87,321 86,319 85,318 84,318 82,318 81,318 80,318 78,318 77,319 76,320 74,322 73,324 72,325 72,327 71,329 70,331 70,332 69,333 69,334 69,335 68,334 67,333 66,332 66,331 65</Letter>
   </WordPart>
</root>