<?xml version="1.0" encoding="utf-8"?>
<root ArabicWord="الخزّانات " EnglishWord="AL7RANAB ">
   <WordPart>
      <Letter letter="A">737 64,738 80,738 84,738 88,738 92,738 96,738 99,738 103,737 106,737 109,737 111,736 114,736 116,735 117,735 119,734 120,734 121,733 121,732 121</Letter>
   </WordPart>
   <WordPart>
      <Letter letter="L">707 73,707 85,708 98,707 105,706 107,704 110,703 112,700 114,697 116,694 118,687 120,679 121</Letter>
      <Letter letter="7">679 121,676 121,673 121,670 120,668 119,666 118, Inf Inf,  659 107,658 107,659 106,663 105,665 104,671 104,672 105,671 106,667 111,666 112,666 113,665 114,664 115,663 116,663 117,661 118,660 118,658 119,657 120,654 120,652 121,649 121,647 121</Letter>
      <Letter letter="R">647 121,644 120,642 120,639 119,637 119,635 118,634 117,632 116,631 115,630 115,630 114,630 113,629 113,629 112,629 113,630 113,630 114,630 116,631 118,631 120,632 122,633 125,633 127,633 130,633 132,633 135,632 137,631 139,629 140,628 142,625 143,623 143,621 144,618 144,616 143,614 142,612 141,611 140</Letter>
   </WordPart>
   <WordPart>
      <Letter letter="A">587 67,587 65,587 71,588 78,588 86,589 97,590 107,590 108,590 110,590 111,589 111</Letter>
   </WordPart>
   <WordPart>
      <Letter letter="N">571 105,573 108,572 114,568 118,557 120,554 119,551 118</Letter>
      <Letter letter="A">551 118,548 117,545 116,543 114,540 112,538 109,536 106,535 103,534 100,533 97,532 94,532 90,531 87,531 84,531 81,531 79,531 77,531 76,530 75,530 74</Letter>
   </WordPart>
   <WordPart>
      <Letter letter="B">509 108,510 111,510 115,509 118,508 120,503 122,497 122,493 122,489 122,484 122,479 121,474 120,469 119,465 117,461 116,458 114,455 112,453 110,452 108,451 106,451 104,452 102,453 100,454 99,456 98,458 97</Letter>
   </WordPart>
</root>