<?xml version="1.0" encoding="utf-8"?>
<root ArabicWord="سند حدّاد" EnglishWord="SND 7DAD">
   <WordPart>
      <Letter letter="S">585 107,585 87,586 86,587 91,588 95,588 98,589 103,590 107,591 111,591 114,591 118,591 121,588 124,586 125,584 126,581 125,578 124,576 122,573 120,570 117,568 114,566 111,565 108,564 105,563 103,563 101,563 100,563 99,564 102,565 106,565 108,566 111,567 113,567 116,567 118,567 120,566 121,566 122,565 123,563 123,562 122,560 122,558 120,555 119,553 117,551 114,549 112,547 109,546 107,545 105,544 103,544 102,543 101,544 102,544 104,545 105,546 107,547 110,547 112,548 114,548 116,548 118,544 121</Letter>
      <Letter letter="N">544 121,543 121,541 121,539 120,537 119,534 118,532 117,531 115,529 114,528 112,527 111,527 109,526 108,526 106,526 105,526 104,526 103,525 102,525 101,525 100,525 99,525 98,525 100,526 104,526 106,526 108,526 110,527 112,527 114,527 115,526 117,526 119,525 120,525 121</Letter>
      <Letter letter="D">525 121,524 122,523 122,522 122,521 122,519 122,518 121,517 120,515 119,514 117,513 115,511 113,510 111,509 109,508 106,507 104,506 102,505 100,504 98,504 97,503 95,503 94,503 95,503 96</Letter>
   </WordPart>
   <WordPart>
      <Letter letter="7">504 106,504 107,505 108,505 111,504 115,502 118,498 122,492 125,487 125,484 125,482 124,479 122,477 121,475 118,474 115,473 112,473 109,473 106, Inf Inf, 400 109,400 104,404 101,406 100,410 98,413 98,415 97,422 96,426 96,431 95,435 95,440 94,444 94,448 93,452 92,455 91,458 91,460 90,461 89,462 88,461 88,460 88,458 88,456 89,454 90,451 91,448 93,445 95,441 97,438 100,434 102,431 105,428 107,425 110,422 112,419 114,416 115,413 117,410 118,407 119,404 120,400 121,397 121,393 122,390 122,387 122,384 122</Letter>
      <Letter letter="D">384 122,381 121,379 120,377 118,375 116,374 114,373 111,372 108,371 105,371 103,371 100,370 98,370 97,370 96,370 95,370 96,371 97,371 99,371 101,371 103,371 105,371 108,371 111,370 113,369 116,368 118,367 120,366 122,364 123,362 124,360 124,358 123,355 123,353 121,350 120,348 118</Letter>
   </WordPart>
   <WordPart>
      <Letter letter="A">322 91,325 64,325 62,325 61,326 60,326 59,326 60,326 61,326 63,326 65,326 69,326 72,326 77,326 82,326 88,326 94,325 100,325 106,325 112,325 118,325 122,325 126</Letter>
   </WordPart>
   <WordPart>
      <Letter letter="D">282 93,281 89,281 88,282 88,283 89,284 89,285 90,287 91,288 92,290 93,292 94,293 96,294 97,296 101,296 103,296 105,296 106,295 109,294 111,292 113,289 115,287 117,284 118,280 120,277 121,273 121,270 121,267 119</Letter>
   </WordPart>
</root>