<?xml version="1.0" encoding="utf-8"?>
<root ArabicWord="مجاز الباب" EnglishWord="M7AR ALBAB">
   <WordPart>
      <Letter letter="M">740 108,736 112,736 114,737 116,739 117,741 117,743 117,747 116,748 115,749 114,749 113,749 111,748 110,746 107,744 106,743 106,742 107,740 108,739 109,738 110,737 111,736 113,735 114,734 115,732 117,731 118,729 118,726 119,724 120,721 120,718 120,715 120,712 120,710 119,708 119</Letter>
      <Letter letter="7">708 119,706 119,705 118,704 117,703 117, Inf Inf,  685 107,702 106,703 106,702 107,702 108,701 109,700 109,700 110,699 111,698 113,698 114,697 115,695 116,694 117,692 119,691 119,688 120,686 121,684 121,682 121</Letter>
      <Letter letter="A">682 121,680 121,678 121,677 120,675 119,674 118,673 116,672 114,671 112,670 109,669 106,668 103,668 99,667 95,667 91,666 88,666 85,665 82,665 81,665 79,665 78,665 79,665 81,666 83,667 85,667 88</Letter>
   </WordPart>
   <WordPart>
      <Letter letter="R">646 120,652 134,652 139,649 142,647 144,644 145,641 146,638 147,634 147,631 147,627 147,625 147,622 146,620 144</Letter>
   </WordPart>
   <WordPart>
      <Letter letter="A">588 76,586 71,586 70,586 69,586 70,586 72,587 74,587 76,588 79,589 83,590 87,591 91,593 99,593 103,594 106,595 109,596 112,596 114,596 116,596 117</Letter>
   </WordPart>
   <WordPart>
      <Letter letter="L">577 85,572 79,572 81,572 83,572 85,573 92,573 95,574 98,574 101,574 104,574 106,573 109,573 111,572 113,571 114,569 115,568 116,567 116</Letter>
      <Letter letter="B">567 116,565 117,564 117,563 116,561 115,560 114,560 113,559 112,558 111,558 110,558 109,558 108,557 108,557 109,557 110,557 111,557 112,557 113,557 114,556 115,556 116,555 116,553 117,552 118,550 119,548 119,545 120,543 120,540 120,537 120</Letter>
      <Letter letter="A">537 120,535 119,532 119,530 118,528 117,526 115,525 114,524 112,523 109,523 107,522 103,522 100,522 97,522 93,521 89,521 86,521 83,521 81,521 79,521 78,521 77,522 78,523 79,524 81,525 84</Letter>
   </WordPart>
   <WordPart>
      <Letter letter="B">498 111,499 116,494 119,488 121,484 121,476 122,472 121,468 121,464 120,460 118,457 117,455 115,453 114,452 112,451 111,451 109,451 108,452 107,453 107,455 108,456 108</Letter>
   </WordPart>
</root>