<?xml version="1.0" encoding="utf-8"?>
<root ArabicWord="متلين" EnglishWord="MBLYN">
   <WordPart>
      <Letter letter="M">634 55,633 52,634 52,635 53,636 54,638 55,639 56,641 57,643 58,644 59,646 60,647 61,650 66,651 67,651 68,651 69,650 70,649 70,648 71,647 71,646 71,644 71,643 71,641 71,640 71,638 70,637 70,636 69,635 68,634 67,633 66,633 65,632 64,632 62,631 61,631 60,631 59,630 58,630 57,630 56,629 57,629 58,629 59,629 60,629 61,628 63,628 65,628 66,627 68,626 69,625 71,624 72,623 73,622 74,620 75,619 76,617 77,616 77,614 78,613 78</Letter>
      <Letter letter="B">613 78,611 78,609 77,607 77,606 76,604 75,603 75,601 74,600 73,599 71,598 70,597 69,596 68,595 67,594 66,594 65,593 64,592 63,592 64,592 65,592 66,592 67,593 69,593 70,593 71,593 72,593 73,593 74,593 75,592 76,591 77,590 78,589 79,587 79,586 80,584 81,582 81,580 81</Letter>
      <Letter letter="L">580 81,578 81,577 81,575 81,573 80,572 80,570 79,569 79,568 78,567 77,566 75,565 74,565 72,564 70,563 68,562 65,561 62,560 60,559 57,558 54,557 51,557 48,556 46,556 44,555 42,555 40,554 38,554 37,554 36,553 36,553 37,554 39,554 40,555 42,555 44,556 46,556 49,557 51,557 54,558 56,558 59,559 61,559 64,559 66,559 68,559 70,559 72,559 73,558 75,558 76,557 77,556 77,555 78,554 78</Letter>
      <Letter letter="Y">554 78,552 78,551 78,550 78,548 78,547 77,545 77,544 76,543 76,542 75,541 74,540 73,539 72,538 71,538 70,537 69,537 68,536 68,536 67,536 68,536 69,536 70,536 71,536 72,536 73,536 74,535 76,535 77,535 78,534 78,533 79,532 80,531 81,529 81</Letter>
      <Letter letter="N">529 81,528 82,526 82,524 82,523 82,521 82,520 82,518 81,516 81,515 80,513 79,512 78,511 78,510 77,509 76,508 75,507 73,506 72,505 71,504 71,504 70,503 69,503 70,503 71,504 72,504 73,505 74,506 75,507 76,507 77,508 79,508 80,509 82,509 83,509 85,509 86,508 88,507 89,506 91,505 92,503 94,501 95,499 96,496 97,492 98,489 99,485 99,481 99,477 99,474 99,470 99,467 98,465 97,462 96,461 94,459 92,458 90,458 88,458 85,459 82,460 79,462 76,464 72,468 69,471 65,475 62</Letter>
   </WordPart>
</root>