<?xml version="1.0" encoding="utf-8"?>
<root ArabicWord="مركز العلوي" EnglishWord="MRKR AL3LWY">
   <WordPart>
      <Letter letter="M">594 48,596 51,599 53,605 57,609 59,612 63,615 66,616 68,617 69,618 71,618 72,618 73,618 74,618 75,618 76,617 76,616 77,614 77,613 77,612 76,610 76,609 75,607 74,606 72,604 71,603 69,601 67,600 65,598 63,597 62,596 60,595 58,594 57,593 55,592 54,592 53,591 53,591 52,591 53,591 54,591 55,592 57,592 58,592 60,592 61,592 63,592 65,592 67,592 68,591 70,591 71,590 72,590 73</Letter>
      <Letter letter="R">590 73,589 74,588 74,586 74,585 74,584 74,582 73,580 72,579 71,577 70,575 68,573 66,572 65,570 63,569 62,568 61,567 60,567 59,566 58,567 58,567 59,568 60,569 61,570 62,571 63,572 65,573 67,575 69,576 71,578 74,579 76,580 79,581 81,582 84,582 87,582 89,582 91,582 94,582 96,581 98,579 101,577 103,575 104,572 106,568 107,564 108,560 109,555 109,549 110,544 110,538 109,533 109,527 108,522 107,517 105,513 103</Letter>
   </WordPart>
   <WordPart>
      <Letter letter="K">501 49,504 53,509 58,515 63,518 67,519 68,520 70,521 71,521 73,521 74,521 75,520 76,519 76,518 77</Letter>
      <Letter letter="R">518 77,516 77,515 77,512 77,510 76,508 75,505 75,503 74,500 73,498 72,496 70,495 69,493 68,492 68,492 67,491 66,492 66,493 67,493 68,494 69,496 70,497 72,498 74,500 76,502 78,503 80,505 83,506 85,508 87,509 90,510 93,510 95,511 98,511 100,510 103,509 105,508 108,506 110,503 112,500 114,497 115,493 117,488 118,484 118,479 119,474 119,469 119,464 119,459 118,455 117,451 116,448 114,445 112</Letter>
   </WordPart>
   <WordPart>
      <Letter letter="A">406 26,404 24,404 25,405 26,409 35,420 58,422 62,424 66,425 69,427 73,428 76,430 79,430 81,431 83,432 84,433 85</Letter>
   </WordPart>
   <WordPart>
      <Letter letter="L">383 19,389 34,399 52,401 55,402 58,403 61,404 63,405 66,406 68,407 71,407 73,407 75,407 77,407 78,407 79,407 80,406 81,404 81,403 81,402 81,400 80</Letter>
      <Letter letter="3">400 80,398 80,396 79,394 77,392 76,389 74,387 72,384 70,381 68,378 66,376 64,373 62,371 60,368 59,366 57,365 57,363 56,361 55,360 55,359 55,358 56,357 56,356 57,356 58,357 59,357 60,358 61,359 61,360 62,362 62,364 62,366 62,367 61,369 61,370 60,372 59,373 58,374 57,374 56,374 55,374 54,374 55,375 55,375 56,375 57,376 58,376 59,377 61,378 62,379 64,380 65,380 67,381 68,381 70,381 71,381 72,381 73,380 74,380 75,378 76,377 77,375 78,373 78,371 79,369 80,366 80,364 81,361 81,358 82,355 82,352 82,350 83</Letter>
      <Letter letter="L">350 83,347 83,344 83,342 82,340 82,337 81,335 80,333 79,331 78,329 76,327 74,325 72,323 70,321 67,320 64,318 61,316 58,315 55,313 52,312 49,311 45,309 42,308 39,307 36,306 34,305 32,304 30,304 29,303 29,303 28,303 29,304 30,304 32,305 33,306 35,307 38,308 40,309 43,310 45,311 48,313 50,314 53,315 55,321 68,321 70,322 72,322 74,322 76,322 77,322 79,322 80,321 82,320 83</Letter>
      <Letter letter="W">320 83,319 84,318 85,317 86,315 87,314 87,312 87,310 88,308 88,306 87,303 87,301 86,298 86,296 84,293 83,290 81,288 80,285 78,283 76,281 74,280 73,279 71,277 70,277 68,276 67,276 66,276 65,277 64,278 64,279 64,280 65,282 66,284 67,286 68,288 69,290 71,292 73,295 75,297 77,300 79,302 82,304 84,306 86,308 88,309 90,311 93,311 95,312 97,312 99,312 101,311 103,310 105,308 107,306 108,303 110,299 111,295 112,291 112,286 112,281 112,276 112,271 111,266 110,261 109</Letter>
   </WordPart>
   <WordPart>
      <Letter letter="Y">236 70,221 67,215 71,223 77,226 78,229 79,231 79,234 80,237 81,239 82,241 83,242 84,243 86,243 87,242 89,232 97,230 98,227 99,225 99,222 100,219 100,217 100,214 100,212 100,209 99,206 98,203 96,200 95,197 93,193 91,190 88,186 86,183 83,179 81,176 78,173 76,171 74,168 72,167 70,165 69,164 68,163 67,162 67,161 66,161 67,161 68,162 70,162 71</Letter>
   </WordPart>
</root>