<?xml version="1.0" encoding="utf-8"?>
<root ArabicWord="حامّة الجريد" EnglishWord="7AMH AL7RYD">
   <WordPart>
      <Letter letter="7">587 98,583 92,583 91,582 89,584 87,590 85,596 83,618 81,622 81,626 81,628 80,631 80,632 80,634 80,634 79,633 79,632 79,630 80,628 81,625 83,622 86,618 88,615 92,611 95,607 99,602 103,598 106,594 110,590 112,586 115,583 117,580 118,577 119,574 120</Letter>
      <Letter letter="A">574 120,571 120,568 120,566 119,563 118,561 117,559 115,558 113,556 110,556 107,555 103,555 99,555 94,555 89,555 83,555 78,555 72,554 67,554 62,553 57,553 53,552 50,552 47,551 45,551 44,551 43,551 44,552 46,552 49,552 52,553 57,553 62,553 68</Letter>
   </WordPart>
   <WordPart>
      <Letter letter="M">504 113,504 102,507 96,511 95,515 96,519 98,521 99,523 101,524 102,526 104,526 106,527 107,527 108,527 110,526 111,525 112,523 112,521 113,519 113,517 113,514 112,512 111,509 110,507 108,505 106,503 105,502 103,501 101,501 100,500 99,501 100,501 102,502 103,503 105,503 106,503 108,504 110,504 111,504 112,503 113,503 114,502 115,501 115</Letter>
      <Letter letter="H">501 115,499 115,498 115,496 114,493 113,491 112,489 111,487 110,485 108,483 107,482 106,481 105,481 104,480 103,480 102,481 103,481 104,482 105,482 106,483 107,483 109,483 110,483 111,483 113,483 114,482 115,481 116,479 117,477 118,475 119,472 120,469 120,465 120,461 120,457 120,453 120,449 119,445 118,442 117,439 116,437 115,435 114,434 113,434 111,434 110,435 110,437 109,439 108,442 108,445 107,449 107,453 106,458 106,462 106,467 105,471 105</Letter>
   </WordPart>
   <WordPart>
      <Letter letter="A">378 112,378 92,377 77,376 74,375 72,374 70,374 68,373 67,373 66,372 66,373 67,373 69,373 71,374 73,375 76,376 80,376 84,377 89,378 93,379 97,379 102,379 105,379 109</Letter>
   </WordPart>
   <WordPart>
      <Letter letter="L">344 78,342 73,341 72,342 73,343 79,344 82,349 98,350 101,350 104,350 107,350 109,349 111</Letter>
      <Letter letter="7">349 111,348 112,346 113,344 114,343 114,341 113, Inf Inf,  311 101,306 96,305 93,306 91,307 90,308 90,322 86,324 86,326 85,328 85,330 85,331 84,332 84,333 84,334 84,334 83,334 84,333 85,332 86,331 87,329 88,327 90,325 92,323 94,320 97,318 99,315 102,313 104,311 106,309 108,308 109</Letter>
      <Letter letter="R">308 109,306 110,305 111,304 111,303 111,302 111,302 112,301 113,301 114,301 115,301 117,301 119,301 122,301 124,302 127,302 130,302 132,302 135,301 137,301 140,299 142,298 144,295 146,293 148,289 149,286 151,282 152,278 153,274 154,270 154,266 154,263 154,260 153,258 152,256 150,256 149,257 148</Letter>
   </WordPart>
   <WordPart>
      <Letter letter="Y">271 101,269 97,269 95,268 94,267 92,267 91,268 92,270 96,272 109,271 111,270 113,269 115,268 117,266 118,264 119,262 120,259 120,257 120,255 119,252 118</Letter>
      <Letter letter="D">252 118,250 117,248 114,246 112,245 109,243 106,242 103,241 101,240 99,239 97,238 96,237 95, Inf Inf,  239 108,240 110,240 111,238 114,232 120,227 123,220 124,218 123,217 122,215 121,214 119,213 118,213 116</Letter>
   </WordPart>
</root>