<?xml version="1.0" encoding="utf-8"?>
<root ArabicWord="عين زريق" EnglishWord="3YN RRYF">
   <WordPart>
      <Letter letter="3">651 104,652 102,651 102,644 101,639 102,636 103,635 104,635 105,635 106,635 107,636 108,637 108,638 109,639 110,641 111,643 112,645 112,647 113,649 113,650 114,652 115,653 115,654 116,655 117,654 117,654 118,653 118,652 119,651 119,649 119,648 120,642 121,639 121,637 121,635 120</Letter>
      <Letter letter="Y">635 120,632 120,630 120,628 119,626 119,624 118,622 117,621 116,620 116,619 115,618 114,617 114,617 113,617 112,617 113,617 114,617 115,617 116,617 117,617 118,617 119,616 119,615 120,613 120,611 121,609 121,605 121,601 122</Letter>
      <Letter letter="N">601 122,597 122,593 122,589 121,584 121,580 121,577 120,574 120,571 119,569 119,567 119,566 118,565 118,564 118,565 118,565 119,566 120,566 121,567 123,568 124,569 126,570 128,571 130,572 132,572 134,573 136,573 138,573 139,573 141,572 142,571 143,569 144,566 145,563 145,559 145,554 145,549 145,544 145,538 144,532 144,527 143,522 142,517 141,512 139,509 138,505 137,502 135,500 134,498 132,496 130,495 128,494 126,493 124,493 122,493 120,493 118,494 116,495 114,496 113,498 111,500 110,502 109,505 108,507 108,510 108,513 108,516 108,520 108</Letter>
   </WordPart>
   <WordPart>
      <Letter letter="R">457 120,459 121,462 125,465 131,469 140,469 141,469 142,469 144,468 145,467 146,465 147,463 148,461 149,458 150,455 151,451 151,447 152,443 152,439 152,434 152,430 152,426 152,422 152,419 152,416 152,414 151,412 150,411 148</Letter>
   </WordPart>
   <WordPart>
      <Letter letter="R">387 113,386 116,389 121,392 126,393 131,393 133,393 135,393 137,393 138,392 140,391 141,389 142,388 144,386 145,383 146,380 147,378 148,374 149,371 150,367 151,363 151,360 152,356 152,353 152,349 152,346 151,344 150</Letter>
   </WordPart>
   <WordPart>
      <Letter letter="Y">331 104,333 108,337 113,340 118,339 121,338 121,337 122,335 122,333 123,331 123,328 123,325 124,321 124,318 124,313 125,309 125,304 125</Letter>
      <Letter letter="F">304 125,300 125,295 126,290 126,285 126,280 126,276 126,271 125,268 125,264 125,262 124,260 124,258 123,257 122,256 121,256 120,255 119,256 118,256 117,257 116,257 115,258 114,259 114,261 114,262 114,263 114,265 114,266 114,268 115,269 116,271 117,272 118,274 119,275 121,277 123,278 124,279 126,280 128,281 130,281 131,281 133,281 135,281 136,280 137,279 139,278 140,276 141,274 142,272 143,269 144,266 145,263 145,259 146,255 146,251 146,247 146,242 146,238 146,233 145,229 144,225 143,221 142,218 140,214 138,211 136,208 133,206 130,204 128,202 125,201 122,200 119,200 116,200 114,201 112,202 110,205 109,207 108,211 107,215 105,219 104,224 103</Letter>
   </WordPart>
</root>