<?xml version="1.0" encoding="utf-8"?>
<root ArabicWord="سيدي بنّور" EnglishWord="SYDY BNWR">
   <WordPart>
      <Letter letter="S">727 105,727 99,727 102,727 110,727 112,727 114,727 116,727 117,726 118,725 119,725 120,724 121,723 121,722 121,721 121,720 121,719 120,718 119,717 118,716 117,716 116,715 114,715 113,714 112,714 111,714 110,714 111,714 112,714 113,714 115,713 116,713 117,713 119,712 120,712 121,711 121,711 122,710 122,709 122,709 121,708 121,708 120,707 119,707 118,707 117,706 116,706 115,706 114,705 113,705 112,705 113,706 114,706 115,706 116,706 117,706 118,705 118,705 119,704 119,702 120,700 120,698 120,696 120,693 120</Letter>
      <Letter letter="Y">693 120,691 120,688 120,685 120,682 120,680 120,678 119,676 119,675 118,673 117,672 116,671 115,671 114,670 113,670 112,670 111,670 110,670 109,670 110,670 111,670 112,670 113,671 113,671 114,671 115,671 116,671 117,670 118,669 119,668 120</Letter>
      <Letter letter="D">668 120,666 120,665 120,663 120,662 120,660 120,659 120,657 119,656 119,655 118,654 118,653 117,653 116</Letter>
   </WordPart>
   <WordPart>
      <Letter letter="Y">644 106,645 106,646 109,647 111,649 114,650 117,647 119,646 119,644 118,643 118,642 117,640 117,640 116,639 115,638 115</Letter>
   </WordPart>
   <WordPart>
      <Letter letter="B">628 117,625 115,623 114,618 115,615 122,616 125,621 130,623 131,624 132,624 133,624 134,624 136,624 137,623 138,621 139,619 139,616 140,613 140,610 140,607 139,603 139,600 138,597 136,594 134,591 132,589 129,588 127,587 124,587 122,587 119,588 117,589 116,590 114,592 114,594 113, Inf Inf, 564 107,565 112,565 116,565 119,560 122,558 123,555 124,552 124,549 125</Letter>
      <Letter letter="N">549 125,547 125,544 125,541 125,538 125,536 125,533 125,532 124,530 124,529 123,528 122,527 121,527 120,527 119,527 118,526 118,526 117,526 116,526 115,526 116,526 117,526 118,525 119,525 120,524 120,523 121,522 122,521 123,520 123,518 124,516 125,513 125,511 126</Letter>
      <Letter letter="W">511 126,508 126,505 127,502 127,499 127,496 126,494 126,491 125,489 124,488 123,487 123,486 122,485 121,485 120,485 119,485 118,486 118,487 118,488 118,490 118,491 119,492 120,493 122,495 123,496 125,497 128,498 131,499 134,499 137,499 140,499 143,498 145,496 148,494 151,491 153,487 155,484 157,479 158,475 159,471 160,467 160,464 160,462 159,460 158,459 156</Letter>
   </WordPart>
   <WordPart>
      <Letter letter="R">443 116,444 120,446 127,446 133,438 145,435 147,431 149,428 150,424 152,420 153,416 154,412 155,409 155,406 155,403 155</Letter>
   </WordPart>
</root>