<?xml version="1.0" encoding="utf-8"?>
<root ArabicWord="سيدي بوزيد" EnglishWord="SYDY BWRYD">
   <WordPart>
      <Letter letter="S">705 90,706 93,711 101,709 112,708 113,705 114,704 115,700 113,699 112,699 111,698 108,697 106,697 105,696 103,696 101,695 100,695 99,695 98,695 97,695 98,695 99,695 101,694 102,694 104,694 105,693 107,693 108,692 110,691 111,691 112,690 112,689 113,688 113,686 113,685 113,684 113,682 113,681 112,679 111,678 110,677 108,676 107,676 106,676 104,675 103,675 102,675 101,675 100,675 101,675 102,675 104,675 105,674 106,674 108,673 109,672 110,671 111,669 112,668 113,666 114,664 114,662 114,659 114</Letter>
      <Letter letter="Y">659 114,657 114,655 113,653 112,651 111,648 109,647 107,647 106,646 104,646 103,646 102,646 101,645 102,645 103,645 104,645 105,644 106,644 107,643 109,642 110,641 112,640 113,638 114,636 114,634 115,632 115</Letter>
      <Letter letter="D">632 115,629 116,626 116,623 115,620 115,617 114,614 113,611 112,609 111,607 110,605 109,604 108,603 107,602 106,601 105,602 106,602 107,602 108,602 109,603 110,603 111,603 113,603 114,603 115,603 116,602 116,601 117,599 118,598 118,596 118,594 119,591 119,589 119,587 119,584 119,582 119,581 119,579 119,578 119,577 119,576 117,575 116,574 115,573 114</Letter>
   </WordPart>
   <WordPart>
      <Letter letter="Y">565 116,562 117,560 117,559 118,558 119,557 119,557 120,557 121,556 123,555 125,554 127,553 128,544 133,540 135,536 137,531 138,526 139,521 140,517 141,512 141,509 141,506 140,504 139,503 137,503 134,504 131,505 129,507 126,509 123,512 120,516 118,519 116,522 114,525 113,528 113</Letter>
   </WordPart>
   <WordPart>
      <Letter letter="B">447 105,451 108,454 110,455 112,456 115,453 120,434 125</Letter>
      <Letter letter="W">434 125,429 126,424 126,420 125,416 125,413 124,410 123,409 122,409 120,409 119,410 118,412 117,414 116,416 116,418 116,421 117,423 117,426 118,428 120,429 121,431 123,431 124,432 126,432 128,431 130,430 133,429 135,427 138,424 140,420 143,416 145,412 147,408 149,404 151,400 152,396 152,393 153,391 152,389 151,388 150,388 148,389 146,389 143,390 140,392 137</Letter>
   </WordPart>
   <WordPart>
      <Letter letter="R">374 106,380 118,378 132,376 134,373 135,370 137,366 137,362 138,358 138,353 137,350 136,346 134,343 132,341 129,340 126,339 122</Letter>
   </WordPart>
   <WordPart>
      <Letter letter="Y">317 104,313 102,315 106,316 111,314 114,311 117,298 121,296 121,294 121,292 121,290 120</Letter>
      <Letter letter="D">290 120,289 119,288 118,287 117,286 115,285 113,284 112,283 110,283 109,282 107, Inf Inf,  270 104,272 105,274 106,276 108,278 110,279 112,281 114,282 116,283 117,283 119,283 121,282 122,279 124,277 125,275 125,273 126,270 126,268 126,266 126,264 125,263 124,262 122,262 121,261 119,261 116,261 113,261 110</Letter>
   </WordPart>
</root>