<?xml version="1.0" encoding="utf-8"?>
<root ArabicWord="المرجى " EnglishWord="ALMR7Y ">
   <WordPart>
      <Letter letter="A">646 56,646 54,646 53,646 52,646 57,646 65,646 72,647 80,647 90,647 93,648 95,648 98,648 100,648 102,648 104,649 106,649 107,649 108,649 107,649 105,649 104</Letter>
   </WordPart>
   <WordPart>
      <Letter letter="L">623 61,622 60,621 59,621 60,622 61,622 62,622 63,623 65,623 67,624 70,624 73,625 76,625 79,626 83,626 92,626 95,625 98,624 100,623 102,622 104,621 106,619 108,618 109,617 110</Letter>
      <Letter letter="M">617 110,616 110,615 111,614 111,613 111,612 111,612 110,611 109,610 108, Inf Inf,  601 102,611 106,610 112,609 112,607 113,606 113,605 113,604 112,603 112,602 111,602 110,601 108,601 107,601 106,601 104,601 103,601 102,602 101,602 102,601 103,601 104,601 105,600 106,599 107,598 108,597 109,595 110,593 111,591 112,589 113,586 113,583 113,580 113</Letter>
      <Letter letter="R">580 113,576 113,573 113,569 112,566 112,563 111,561 110,559 110,558 109,557 109,556 109,557 110,557 111,558 111,558 112,559 113,559 114,560 115,560 117,560 118,560 119,560 121,560 122,559 123,558 125,557 126,556 128,554 129,553 130,551 132,550 133,548 133,547 134,545 135,544 135,543 136,542 136,540 136,539 136,537 135,535 134,533 133,531 132,529 130,526 129,523 126</Letter>
   </WordPart>
   <WordPart>
      <Letter letter="7">476 107,473 106,473 103,473 102,474 100,475 99,482 101,484 101,486 102,489 102,491 103,494 103,496 103,498 103,499 104,500 104,501 104,502 104,501 104,501 105,500 105,499 106,497 106,495 107,493 108,491 109,488 110,486 111,483 113,480 113,478 114,475 115,473 116</Letter>
      <Letter letter="Y">473 116,471 117,469 118,468 119,467 120,466 121,465 122,465 123,465 124,465 125,464 126,464 127,464 128,463 129,462 130,460 131,458 132,456 133,453 135,449 136,445 137,441 138,436 139,432 140,427 140,423 140,420 140,417 139,415 137,413 136,412 133,412 131,413 128,415 125,417 122,420 120,423 117,427 115,430 114,434 112</Letter>
   </WordPart>
</root>