<?xml version="1.0" encoding="utf-8"?>
<root ArabicWord="قرنبالية الزّهور" EnglishWord="FRNBALYH ALRHWR">
   <WordPart>
      <Letter letter="F">629 107,593 104,591 100,591 99,591 97,591 95,592 93,594 92,595 91,597 90,599 90,601 91,604 92,606 93,608 95,611 97,613 99,614 101,615 103,616 106,616 108,615 110,614 111,612 113,610 114,607 116,603 117,600 118,596 118,592 118,588 118</Letter>
      <Letter letter="R">588 118,584 118,581 117,577 116,574 115,572 114,570 112,568 111,567 111,567 110,568 111,569 112,571 114,572 116,575 118,577 121,579 125,581 128,583 132,584 136,585 141,585 145,584 150,582 154,579 158,576 162,572 165,568 168,563 170,557 172,552 173,546 174,541 174,535 174,530 173,525 172,520 170,517 168,514 165,512 162</Letter>
   </WordPart>
   <WordPart>
      <Letter letter="N">523 97,525 90,526 86,527 85,527 86,527 87,528 88,528 92,529 95,529 98,529 104,529 114,529 117,529 119,528 121,528 123,527 124,525 125,524 125,522 125,519 125</Letter>
      <Letter letter="B">519 125,516 125,514 124,511 122,508 121,506 119,504 116,503 114,502 112,501 110,501 108,500 106,500 105,501 105,501 106,502 107,502 108,502 110,502 111,501 112,501 113,500 114,498 116,497 117,495 118,492 119,489 119,486 120,482 120,478 120,474 120,469 120,464 120,459 120,454 119,449 119,444 119</Letter>
      <Letter letter="A">444 119,439 118,434 118,430 117,425 116,422 115,418 113,416 112,413 109,411 106,410 103,408 99,407 95,406 90,406 85,405 80,405 75,404 70,404 64,404 60,404 55,404 51,404 48,404 45,404 43,404 41,404 40,405 40,406 40</Letter>
   </WordPart>
   <WordPart>
      <Letter letter="L">381 101,382 49,381 44,381 45,381 46,382 49,382 52,382 57,383 62,383 67,383 74,383 80,383 86,383 91,383 97,383 101,382 105,382 108,382 111,381 113,380 115,378 116,377 116</Letter>
      <Letter letter="Y">377 116,375 116,372 115,370 114,367 112,365 110,362 108,360 105,358 103,357 101,356 99,356 98,355 98,355 99,356 100,356 101,356 104,356 106,356 108,356 110,356 112,355 114,354 115,352 116</Letter>
      <Letter letter="H">352 116,350 116,348 115,346 114,344 113,342 111,340 109,338 108,337 106,336 105,336 104,335 105,335 106,336 107,336 108,336 110,335 111,334 113,333 114,332 115,330 116,327 117,324 118,320 118,316 118,312 118,307 118,303 118,299 117,295 116,292 115,289 115,286 114,285 112,284 112,283 110,283 109,284 108,286 107,288 105,291 104,294 103,298 102,303 101,307 100,313 100,318 100,323 100,328 100,334 100,339 100,344 100</Letter>
   </WordPart>
   <WordPart>
      <Letter letter="A">256 95,257 72,257 59,257 57,257 56,257 57,257 59,257 61,257 65,257 69,257 74,257 80,257 86,257 93,257 99,256 106,256 111,256 117,256 121</Letter>
   </WordPart>
   <WordPart>
      <Letter letter="L">233 69,234 59,236 66,238 78,237 102,235 106,234 110,231 113,229 115,227 117</Letter>
      <Letter letter="R">227 117,224 117,221 117,219 116,216 115,214 113,213 111,211 109,210 108,209 106,208 105,208 104,209 105,209 106,210 108,211 110,212 113,213 117,214 120,214 124,214 128,214 132,213 136,212 139,210 143,207 146,204 149,201 152,197 155,193 157,189 159,184 160,180 161,175 162,171 162,166 161,162 160,158 158,155 154</Letter>
   </WordPart>
   <WordPart>
      <Letter letter="H">156 109,160 115,165 129,165 132,165 137,164 139,163 141,161 142,160 142,158 142,156 142,153 141,151 138,149 136,148 132,146 127,145 122,145 116,145 111,145 106,146 101,147 96,148 93,149 90,150 89,152 88,153 87,155 88,157 88,159 89,161 91,162 92,164 94,165 95,166 97,166 99,166 101,166 103,165 105,164 107,163 109,161 110,159 112,157 114,154 116,151 118,147 121,143 123,138 125,134 127</Letter>
      <Letter letter="W">134 127,129 128,125 130,121 130,117 131,114 130,111 130,109 128,107 126,106 123,105 121,105 118,104 115,104 112,105 110,105 108,106 107,107 106,108 105,110 105,111 106,113 106,115 107,118 109,120 111,122 114,124 117,125 121,126 124,126 129,126 133,126 137,125 142,123 146,121 150,119 154,116 158,113 161,109 164,105 167,101 169,96 171</Letter>
   </WordPart>
   <WordPart>
      <Letter letter="R">83 109,83 106,85 114,86 126,83 142,75 160,64 169,61 171,56 173,52 174</Letter>
   </WordPart>
</root>